LICENSE.md
README.md
setup.py
aciClient/__init__.py
aciClient/aci.py
aciClient/aciCertClient.py
aciClient.egg-info/PKG-INFO
aciClient.egg-info/SOURCES.txt
aciClient.egg-info/dependency_links.txt
aciClient.egg-info/not-zip-safe
aciClient.egg-info/requires.txt
aciClient.egg-info/top_level.txt
test/test_aci.py