Metadata-Version: 2.4
Name: aciClient
Version: 1.7
Summary: aci communication helper class
Home-page: http://www.netcloud.ch
Author: Netcloud AG
Author-email: nc_dev@netcloud.ch
License: MIT
Requires-Python: >=3.10
License-File: LICENSE.md
Requires-Dist: requests[socks]==2.32.5
Requires-Dist: pyOpenSSL==25.3.0
Dynamic: author
Dynamic: author-email
Dynamic: description
Dynamic: description-content-type
Dynamic: home-page
Dynamic: license
Dynamic: license-file
Dynamic: requires-dist
Dynamic: requires-python
Dynamic: summary
